netbox_device_groups/__init__.py
netbox_device_groups/api/__init__.py
netbox_device_groups/api/nested_serializers.py
netbox_device_groups/api/serializers.py
netbox_device_groups/api/urls.py
netbox_device_groups/api/views.py
netbox_device_groups/choices.py
netbox_device_groups/core/__init__.py
netbox_device_groups/core/models/__init__.py
netbox_device_groups/filtersets.py
netbox_device_groups/forms/__init__.py
netbox_device_groups/forms/bulk_edit.py
netbox_device_groups/forms/bulk_import.py
netbox_device_groups/forms/filtersets.py
netbox_device_groups/forms/model_forms.py
netbox_device_groups/graphql/__init__.py
netbox_device_groups/graphql/schema.py
netbox_device_groups/graphql/types.py
netbox_device_groups/migrations/0001_initial.py
netbox_device_groups/migrations/__init__.py
netbox_device_groups/models/__init__.py
netbox_device_groups/models/physical_cluster.py
netbox_device_groups/models/physical_cluster_type.py
netbox_device_groups/navigation.py
netbox_device_groups/search.py
netbox_device_groups/tables.py
netbox_device_groups/templates/netbox_device_groups/cluster_add_devices.html
netbox_device_groups/templates/netbox_device_groups/devicegroup.html
netbox_device_groups/templates/netbox_device_groups/devicegrouptype.html
netbox_device_groups/templates/netbox_device_groups/physical_cluster/base.html
netbox_device_groups/templates/netbox_device_groups/physical_cluster/devices.html
netbox_device_groups/tests/__init__.py
netbox_device_groups/tests/test_filtersets.py
netbox_device_groups/tests/test_forms.py
netbox_device_groups/tests/test_graphql.py
netbox_device_groups/tests/test_models.py
netbox_device_groups/tests/test_views.py
netbox_device_groups/urls.py
netbox_device_groups/views.py
netbox_device_groups-0.1.1.dist-info/LICENSE
netbox_device_groups-0.1.1.dist-info/WHEEL
netbox_device_groups-0.1.1.dist-info/METADATA
netbox_device_groups-0.1.1.dist-info/RECORD
