Metadata-Version: 2.1
Name: netbox-device-groups
Version: 0.1.1
Summary: A netbox plugin for managing multiple device group types
Home-page: https://github.com/sapcc/netbox-device-groups
Keywords: Netbox,netbox,plugin
Author: Pat McLean
Author-email: patrick.mclean@sap.com
Requires-Python: >=3.10,<4.0
Classifier: Development Status :: 5 - Production/Stable
Classifier: Intended Audience :: Developers
Classifier: License :: OSI Approved :: Apache Software License
Classifier: Operating System :: OS Independent
Classifier: Programming Language :: Python :: 3
Classifier: Programming Language :: Python :: 3.10
Classifier: Programming Language :: Python :: 3.11
Classifier: Programming Language :: Python :: 3
Classifier: Programming Language :: Python :: 3.10
Classifier: Programming Language :: Python :: 3.11
Requires-Dist: bleach (==6.1.0)
Requires-Dist: django (==4.2.8)
Requires-Dist: django-cors-headers (==4.3.1)
Requires-Dist: django-debug-toolbar (==4.2.0)
Requires-Dist: django-filter (==23.5)
Requires-Dist: django-graphiql-debug-toolbar (==0.2.0)
Requires-Dist: django-mptt (==0.14.0)
Requires-Dist: django-pglocks (==1.0.4)
Requires-Dist: django-prometheus (==2.3.1)
Requires-Dist: django-redis (==5.4.0)
Requires-Dist: django-rich (==1.8.0)
Requires-Dist: django-rq (==2.10.1)
Requires-Dist: django-tables2 (==2.7.0)
Requires-Dist: django-taggit (==5.0.1)
Requires-Dist: django-timezone-field (==6.1.0)
Requires-Dist: djangorestframework (==3.14.0)
Requires-Dist: drf-spectacular (==0.27.0)
Requires-Dist: drf-spectacular-sidecar (==2023.12.1)
Requires-Dist: feedparser (==6.0.11)
Requires-Dist: graphene-django (==3.0.0)
Requires-Dist: gunicorn (==21.2.0)
Requires-Dist: jinja2 (==3.1.2)
Requires-Dist: markdown (==3.5.1)
Requires-Dist: mkdocs-material (==9.5.3)
Requires-Dist: mkdocstrings[python-legacy] (==0.24.0)
Requires-Dist: netaddr (==0.9.0)
Requires-Dist: pillow (==10.1.0)
Requires-Dist: psycopg[binary,pool] (==3.1.16)
Requires-Dist: pyyaml (==6.0.1)
Requires-Dist: requests (==2.31.0)
Requires-Dist: social-auth-app-django (==5.4.0)
Requires-Dist: social-auth-core[openidconnect] (==4.5.1)
Requires-Dist: svgwrite (==1.4.3)
Requires-Dist: tablib (==3.5.0)
Requires-Dist: tzdata (==2023.3)
Project-URL: Documentation, https://sapcc.github.io/netbox-device-groups
